evaluix/GUIs/Btn_InfoSettings.py
evaluix/GUIs/Btn_InfoSettings.ui
evaluix/GUIs/CustomWidgets.py
evaluix/GUIs/Evaluix2_MainWindowLayout.py
evaluix/GUIs/Evaluix2_MainWindowLayout.ui
evaluix/GUIs/FunctionViewer.py
evaluix/GUIs/FunctionViewer.ui
evaluix/GUIs/HDF5Preview.py
evaluix/GUIs/HDF5Preview.ui
evaluix/GUIs/Icons/__init__.py
evaluix/GUIs/Icons/icon_hys_ArctanEval.png
evaluix/GUIs/Icons/icon_hys_DoubleArctanEval.png
evaluix/GUIs/Icons/icon_hys_LinEval.png
evaluix/GUIs/Icons/icon_hys_center.png
evaluix/GUIs/Icons/icon_hys_del_outliers.png
evaluix/GUIs/Icons/icon_hys_noise_reduction.png
evaluix/GUIs/Icons/icon_hys_norm.png
evaluix/GUIs/Icons/icon_hys_num_derivative.png
evaluix/GUIs/Icons/icon_hys_num_integral.png
evaluix/GUIs/Icons/icon_hys_rmv_opening.png
evaluix/GUIs/Icons/icon_hys_slope_corr.png
evaluix/GUIs/Icons/icon_infosettings.png
evaluix/GUIs/Icons/icon_infosettings_cropped.png
evaluix/GUIs/Icons/icon_trashcan.png
evaluix/GUIs/Icons/icon_trashcan_cropped.png
evaluix/GUIs/Icons/old_icon_infosettings.png
evaluix/GUIs/Icons/old_icon_infosettings_cropped.png
evaluix/GUIs/Icons/resources.qrc
evaluix/GUIs/ManualDataDialog.py
evaluix/GUIs/ManualDataDialog.ui
evaluix/GUIs/ProfileAndMacros.py
evaluix/GUIs/ProfileAndMacros.ui
evaluix/GUIs/__init__.py
evaluix/__init__.py
evaluix/__main__.py
evaluix/__version__.py
evaluix/logs/log.txt
evaluix/logs/logger_2024-10-17.log
evaluix/logs/logger_2024-10-25.log
evaluix/logs/logger_2024-11-01.log
evaluix/logs/logger_2024-11-04.log
evaluix/logs/logger_2024-11-05.log
evaluix/logs/logger_2024-11-06.log
evaluix/logs/logger_2024-11-07.log
evaluix/utils/CreateEvaluixConfig.py
evaluix/utils/DefaultProfile.yaml
evaluix/utils/EvaluationFunctions.py
evaluix/utils/EvaluixConfig.yaml
evaluix/utils/FileLoader.py
evaluix/utils/Macros.yaml
evaluix/utils/__init__.py
evaluix-0.9.3.2.dist-info/LICENSE
evaluix-0.9.3.2.dist-info/METADATA
evaluix-0.9.3.2.dist-info/WHEEL
evaluix-0.9.3.2.dist-info/entry_points.txt
evaluix-0.9.3.2.dist-info/RECORD
