Metadata-Version: 2.1
Name: evaluix
Version: 0.9.3.2
Summary: Data Evaluation Software of the (Magnetism) research group of Prof. Ehresmann at University of Kassel
Home-page: https://github.com/exp4-age/evaluix
License: MIT
Keywords: evaluix,hysteresis
Author: Arne Jan Vereijken
Author-email: arne.vereijken@physik.uni-kassel.de
Requires-Python: >=3.9
Classifier: License :: OSI Approved :: MIT License
Classifier: Programming Language :: Python :: 3
Classifier: Programming Language :: Python :: 3.9
Classifier: Programming Language :: Python :: 3.10
Classifier: Programming Language :: Python :: 3.11
Classifier: Programming Language :: Python :: 3.12
Classifier: Programming Language :: Python :: 3.13
Requires-Dist: NSFopen (>=2.0.0)
Requires-Dist: exp4-agepy (>=0.2)
Requires-Dist: h5py
Requires-Dist: ipykernel (>=6.0.3)
Requires-Dist: ipython_genutils
Requires-Dist: lmfit
Requires-Dist: matplotlib
Requires-Dist: numpy (>=1.24.2)
Requires-Dist: pandas
Requires-Dist: pyqt6 (>=6.4.2)
Requires-Dist: pyyaml
Requires-Dist: scikit-learn
Requires-Dist: scipy
Project-URL: Repository, https://github.com/exp4-age/evaluix
